{
    "dimensions": [
        {
         "name":"dim_ano",
         "levels": [
                {
                    "name":"ano",
                    "label":"Ano",
                    "attributes": ["id", "ano"],
                    "label_attribute": "ano"
                }
          ]
        },
        {
          "name":"dim_carga",
          "levels": [
            {
              "name": "carga",
              "label":"Carga",
              "attributes": ["id", "codigo"],
              "label_attribute": "codigo"
            }
          ]
        }
    ],
    "cubes": [
        {
            "name": "fact_carga",
            "dimensions": ["dim_carga", "dim_ano"],
            "measures": [
              {"name": "cantidad", "label": "Cantidad"}
            ],
            "aggregates": [
              {
                "name": "sumatoria",
                "function": "sum",
                "measure": "cantidad"
              }
            ],
            "joins": [
              {
                "master": "fact_carga.id_carga",
                "detail": "dim_carga.id"
              },
              {
                "master": "fact_carga.id_ano",
                "detail": "dim_ano.id"
              }
            ],
            "mappings": {
              "dim_carga.id": "dim_carga.id",
              "dim_carga.codigo": "dim_carga.codigo",
              "dim_ano.id": "dim_ano.id",
              "dim_ano.codigo": "dim_ano.ano"
            }
        }
    ]
}