{
    "dimensions": [
        {
         "name":"dim_estudiante",
         "levels": [
                {
                    "name":"estudiante",
                    "label":"Estudiante",
                    "attributes": ["id", "cedula", "nombre", "apellido", "sexo", "fecha_nacimiento", "email", "edo_procedencia"],
                    "label_attribute": "nombre"
                }
          ]
        },
        {
          "name":"dim_facultad",
          "levels": [
            {
              "name": "facultad",
              "label":"Facultad",
              "attributes": ["id", "nombre"],
              "label_attribute": "nombre"
            }
          ]
        },
        {
          "name":"dim_carrera",
          "levels": [
            {
              "name": "carrera",
              "label":"Carrera",
              "attributes": ["id", "nombre", "tipo"],
              "label_attribute": "nombre"
            }
          ]
        },
        {
          "name": "dim_status",
          "levels": [
            {
              "name": "status",
              "label": "Status",
              "attributes": ["id", "codigo"],
              "label_attribute": "codigo"
            }
          ]
        },
        {
          "name": "dim_asignatura_inscrita",
          "levels": [
            {
              "name": "status",
              "label": "Status",
              "attributes": ["id", "codigo"],
              "label_attribute": "codigo"
            }
          ]
        }
    ],
    "cubes": [
        {
            "name": "fact_asignatura_inscrita",
            "dimensions": ["dim_estudiante", "dim_facultad", "dim_carrera", "dim_status", "dim_asignatura_inscrita"],
            "measures": [
              {"name": "cantidad", "label": "Cantidad"}
            ],
            "aggregates": [
              {
                "name": "sumatoria",
                "function": "sum",
                "measure": "cantidad"
              }
            ],
            "joins": [
              {
                "master": "fact_asignatura_inscrita.id_estudiante",
                "detail": "dim_estudiante.id"
              },
              {
                "master": "fact_asignatura_inscrita.id_facultad",
                "detail": "dim_facultad.id"
              },
              {
                "master": "fact_asignatura_inscrita.id_carrera",
                "detail": "dim_carrera.id"
              },
              {
                "master": "fact_asignatura_inscrita.id_status",
                "detail": "dim_status.id"
              },
              {
                "master": "fact_asignatura_inscrita.id_asignatura_inscrita",
                "detail": "dim_asignatura_inscrita.id"
              }
            ],
            "mappings": {
              "dim_estudiante.id": "dim_estudiante.id",
              "dim_estudiante.cedula": "dim_estudiante.cedula",
              "dim_estudiante.nombre": "dim_estudiante.nombre",
              "dim_estudiante.apellido": "dim_estudiante.apellido",
              "dim_estudiante.sexo": "dim_estudiante.sexo",
              "dim_estudiante.fecha_nacimiento": "dim_estudiante.fecha_nacimiento",
              "dim_estudiante.email": "dim_estudiante.email",
              "dim_estudiante.edo_procedencia": "dim_estudiante.edo_procedencia",
              "dim_facultad.id": "dim_facultad.id",
              "dim_facultad.nombre": "dim_facultad.nombre",
              "dim_carrera.id": "dim_carrera.id",
              "dim_carrera.nombre": "dim_carrera.nombre",
              "dim_carrera.tipo": "dim_carrera.tipo",
              "dim_status.id": "dim_status.id",
              "dim_status.codigo": "dim_status.codigo",
              "dim_asignatura_inscrita.id": "dim_asignatura_inscrita.id",
              "dim_asignatura_inscrita.codigo": "dim_asignatura_inscrita.codigo"
            }
        }
    ]
}